{
  "contentMap" : {
    "content.json" : {
      "contentChecksum" : "722e8731046d8a6ab9c5effcb8a544db938f2425",
      "contentName" : "content",
      "contentOid" : 19052,
      "contentType" : "json",
      "type" : ".LargeObjectMetadataComponent"
    }
  },
  "deleted" : false,
  "displayOrder" : 0,
  "entitySummary" : false,
  "genericProperties" : {
    "qPropEntry" : {
      "qProperty" : {
        "cells" : [ {
          "col" : 1,
          "colspan" : 22,
          "name" : "HDThZ",
          "row" : 0,
          "rowspan" : 12,
          "type" : "pivot-table"
        } ],
        "columns" : 24,
        "qInfo" : {
          "qId" : "LSZHpfJ",
          "qType" : "sheet"
        },
        "qMetaDef" : {
          "description" : "Compare this year sales with last year  sales.",
          "title" : "Sales Comparison"
        },
        "rank" : 1.5,
        "rows" : 12,
        "thumbnail" : {
          "qStaticContentUrlDef" : {
            "qUrl" : "/appcontent/3a4cdc64-c7f3-4555-b4b1-10a41056730a/Sales Discovery1 - Sales Comparison _ Sheets - Qlik Sense.png"
          }
        }
      }
    },
    "qrsProp" : {
      "approved" : true,
      "owner" : {
        "id" : "2d36aad3-0129-4030-b2a6-31ee823569bc",
        "name" : "Administrator",
        "userDirectory" : "SUPPORT-QLIK1",
        "userId" : "administrator"
      },
      "published" : true,
      "tags" : [ ]
    }
  },
  "hidden" : false,
  "identity" : "LSZHpfJ,Sheet;3a4cdc64-c7f3-4555-b4b1-10a41056730a,App;",
  "key" : {
    "id" : 1363
  },
  "materializedPath" : {
    "namePath" : "My Qlik/Streams/Everyone/Sales Discovery/Sheets/Sales Comparison",
    "subtypePath" : "-/QlikStream/QlikStream/QlikApp/QlikSheet/QlikSheet",
    "typePath" : "PlatformNode/Folder/PlatformArtifact/PlatformArtifact/Folder/PlatformArtifact"
  },
  "name" : "Sales Comparison",
  "nodeKey" : {
    "id" : 26
  },
  "parentKey" : {
    "id" : 275
  },
  "parentRelationType" : "COMPOSITE",
  "path" : {
    "ids" : [ 26, 33, 44, 183, 275, 1363 ]
  },
  "platformType" : "QlikArtifact",
  "platformVersion" : "12.969.2",
  "qlikType" : "Sheet",
  "shouldVersion" : true,
  "subtype" : "QlikSheet",
  "type" : "QlikArtifact"
}